trimmer/__init__.py
trimmer/__main__.py
trimmer/downloader.py
trimmer/main.py
trimmer/metadata.py
trimmer/normalizer.py
trimmer/renamer.py
trimmer/tagger.py
trimmer/trim_source.py
trimmer/upgrade.py
trimmer/version.py
trimmer-1.1.1.dist-info/LICENSE
trimmer-1.1.1.dist-info/METADATA
trimmer-1.1.1.dist-info/WHEEL
trimmer-1.1.1.dist-info/entry_points.txt
trimmer-1.1.1.dist-info/top_level.txt
trimmer-1.1.1.dist-info/RECORD
