Metadata-Version: 2.1
Name: trimmer
Version: 1.1.1
Summary: MP3 song normalizer
Home-page: https://github.com/igrek51/trimmer
Author: igrek51
Author-email: igrek51.dev@gmail.com
License: MIT
Classifier: Programming Language :: Python :: 3
Classifier: License :: OSI Approved :: MIT License
Classifier: Operating System :: OS Independent
Requires-Python: >=3.6.0
License-File: LICENSE
Requires-Dist: pydub >=0.25.1
Requires-Dist: eyeD3 >=0.9.7
Requires-Dist: nuclear >=1.2.3
Requires-Dist: yt-dlp >=2023.3.4
Requires-Dist: youtube-dl >=2021.12.17
